ipybox/__init__.py
ipybox/code_exec.py
ipybox/mcp_apigen.py
ipybox/mcp_client.py
ipybox/mcp_server.py
ipybox/utils.py
ipybox/vars.py
ipybox/kernel_mgr/__init__.py
ipybox/kernel_mgr/client.py
ipybox/kernel_mgr/sandbox.json
ipybox/kernel_mgr/server.py
ipybox/tool_exec/__init__.py
ipybox/tool_exec/client.py
ipybox/tool_exec/server.py
ipybox/tool_exec/approval/__init__.py
ipybox/tool_exec/approval/client.py
ipybox/tool_exec/approval/server.py
ipybox-0.7.2.dist-info/METADATA
ipybox-0.7.2.dist-info/WHEEL
ipybox-0.7.2.dist-info/entry_points.txt
ipybox-0.7.2.dist-info/licenses/LICENSE
ipybox-0.7.2.dist-info/RECORD
