Metadata-Version: 2.4
Name: ipybox
Version: 0.7.2
Summary: ipybox
Author-email: Martin Krasser <martin@gradion.ai>
License-Expression: Apache-2.0
License-File: LICENSE
Requires-Python: <3.15,>=3.11
Requires-Dist: aiofiles>=25.1.0
Requires-Dist: aiohttp>=3.13.2
Requires-Dist: datamodel-code-generator>=0.49.0
Requires-Dist: fastapi>=0.121.2
Requires-Dist: ipykernel>=7.1.0
Requires-Dist: jupyter-kernel-gateway>=3.0.1
Requires-Dist: mcp>=1.21.2
Requires-Dist: pillow>=12.0.0
Requires-Dist: pip>=25.3
Requires-Dist: psutil>=7.1.3
Requires-Dist: python-dotenv>=1.2.1
Requires-Dist: requests>=2.32.5
Requires-Dist: uvicorn>=0.40.0
Requires-Dist: websockets>=15.0.1
Requires-Dist: wsproto>=1.3.2
